KunQuant/Driver.py
KunQuant/Op.py
KunQuant/Stage.py
KunQuant/__init__.py
KunQuant/jit/__init__.py
KunQuant/jit/cfake.py
KunQuant/jit/env.py
KunQuant/ops/CompOp.py
KunQuant/ops/ElewiseOp.py
KunQuant/ops/MiscOp.py
KunQuant/ops/ReduceOp.py
KunQuant/ops/__init__.py
KunQuant/passes/CodegenCpp.py
KunQuant/passes/Decompose.py
KunQuant/passes/ExprFold.py
KunQuant/passes/InferWindow.py
KunQuant/passes/MergeLoops.py
KunQuant/passes/Partitioner.py
KunQuant/passes/SpecialOpt.py
KunQuant/passes/TempWindowElim.py
KunQuant/passes/Util.py
KunQuant/passes/__init__.py
KunQuant/predefined/Alpha101.py
KunQuant/predefined/Alpha158.py
KunQuant/predefined/__init__.py
KunQuant/runner/KunRunner.cp39-win_amd64.pyd
KunQuant/runner/KunRunner.exp
KunQuant/runner/KunRunner.lib
KunQuant/runner/KunRuntime.dll
KunQuant/runner/KunRuntime.exp
KunQuant/runner/KunRuntime.lib
KunQuant/runner/__init__.py
cpp/Kun/Base.hpp
cpp/Kun/Context.hpp
cpp/Kun/CorrWith.hpp
cpp/Kun/IO.hpp
cpp/Kun/LayoutMappers.hpp
cpp/Kun/Math.hpp
cpp/Kun/MathUtil.hpp
cpp/Kun/Module.hpp
cpp/Kun/Ops.hpp
cpp/Kun/Rank.hpp
cpp/Kun/RunGraph.hpp
cpp/Kun/Scale.hpp
cpp/Kun/SkipList.hpp
cpp/Kun/Stage.hpp
cpp/Kun/StateBuffer.hpp
cpp/Kun/StreamBuffer.hpp
cpp/Kun/Ops/Quantile.hpp
cpp/KunSIMD/Vector.hpp
cpp/KunSIMD/cpu/Math.hpp
cpp/KunSIMD/cpu/Table.hpp
cpp/KunSIMD/cpu/cast.hpp
cpp/KunSIMD/cpu/common.hpp
cpp/KunSIMD/cpu/f32x16.hpp
cpp/KunSIMD/cpu/f32x8.hpp
cpp/KunSIMD/cpu/f64x2.hpp
cpp/KunSIMD/cpu/f64x4.hpp
cpp/KunSIMD/cpu/f64x8.hpp
cpp/KunSIMD/cpu/gather.hpp
cpp/KunSIMD/cpu/s32x16.hpp
cpp/KunSIMD/cpu/s32x8.hpp
cpp/KunSIMD/cpu/s64x2.hpp
cpp/KunSIMD/cpu/s64x4.hpp
cpp/KunSIMD/cpu/s64x8.hpp
cpp/KunSIMD/cpu/neon/cast.hpp
cpp/KunSIMD/cpu/neon/common.hpp
cpp/KunSIMD/cpu/neon/f32x4.hpp
cpp/KunSIMD/cpu/neon/f64x2.hpp
cpp/KunSIMD/cpu/neon/gather.hpp
cpp/KunSIMD/cpu/neon/s32x4.hpp
cpp/KunSIMD/cpu/neon/s64x2.hpp
cpp/KunSIMD/cpu/x86/cast.hpp
cpp/KunSIMD/cpu/x86/common.hpp
cpp/KunSIMD/cpu/x86/f32x16.hpp
cpp/KunSIMD/cpu/x86/f32x8.hpp
kunquant-0.1.9.dist-info/licenses/LICENSE
kunquant-0.1.9.dist-info/METADATA
kunquant-0.1.9.dist-info/WHEEL
kunquant-0.1.9.dist-info/top_level.txt
kunquant-0.1.9.dist-info/RECORD
