Metadata-Version: 2.4
Name: KunQuant
Version: 0.1.9
Summary: A compiler, optimizer and executor for financial expressions and factors
Author: Menooker
Author-email: menooker@live.com
License-File: LICENSE
Requires-Dist: numpy
Dynamic: author
Dynamic: author-email
Dynamic: description
Dynamic: description-content-type
Dynamic: license-file
Dynamic: requires-dist
Dynamic: summary
